{
  "name": "Nuggets 38 - Covers 3",
  "slug": "nuggets-38-covers-3",
  "track_count": 24,
  "year_range": "1966–2025",
  "year_min": 1966,
  "year_max": 2025,
  "url": "playlists/nuggets-38-covers-3/",
  "art_thumbnails": [
    "img/01.jpg",
    "img/02.jpg",
    "img/03.jpg",
    "img/04.jpg"
  ],
  "tracks": [
    {
      "title": "Nuggets 38 Intro",
      "artist": "",
      "orig_artist": "",
      "album": "",
      "year": ""
    },
    {
      "title": "Teenage Riot",
      "artist": "Ruby Isle",
      "orig_artist": "Sonic Youth",
      "album": "Into The Black",
      "year": "2007"
    },
    {
      "title": "#9 Dream",
      "artist": "R.E.M.",
      "orig_artist": "Lennon",
      "album": "#9 Dream",
      "year": "2007"
    },
    {
      "title": "Back in the U.S.S.R.",
      "artist": "Liz Green",
      "orig_artist": "Beatles",
      "album": "Mojo Presents: The White Album Recovered (N° 0000001)",
      "year": "2008"
    },
    {
      "title": "Bigmouth Strikes Again",
      "artist": "Placebo",
      "orig_artist": "The Smiths",
      "album": "Covers",
      "year": "2003"
    },
    {
      "title": "Solsbury Hill",
      "artist": "Kyte",
      "orig_artist": "Peter Gabriel",
      "album": "Two Sparks, Two Stars",
      "year": "2011"
    },
    {
      "title": "I'm On Fire",
      "artist": "Coltrane Motion",
      "orig_artist": "Bruce Springsteen",
      "album": "Internet Single",
      "year": "2009"
    },
    {
      "title": "My Body Is a Cage",
      "artist": "Sara Lov",
      "orig_artist": "Arcade Fire",
      "album": "The Young Eyes EP",
      "year": "2009"
    },
    {
      "title": "Felicity",
      "artist": "The Wedding Present",
      "orig_artist": "Orange Juice",
      "album": "Tommy",
      "year": "1997"
    },
    {
      "title": "Can't Hardly Wait",
      "artist": "Justin Townes Earle",
      "orig_artist": "The Replacements",
      "album": "Midnight At The Movies",
      "year": "2009"
    },
    {
      "title": "Another Girl, Another Planet",
      "artist": "The Replacements",
      "orig_artist": "The Only Ones",
      "album": "Closing Time (Live 1991)",
      "year": "2020"
    },
    {
      "title": "Wave Of Mutilation",
      "artist": "Joy Zipper",
      "orig_artist": "Pixies",
      "album": "Dig for Fire: a Tribute to Pixies",
      "year": "2007"
    },
    {
      "title": "Tug Boat",
      "artist": "Sea Power",
      "orig_artist": "Galaxie 500",
      "album": "Independents Day 08",
      "year": "2008"
    },
    {
      "title": "The 15th",
      "artist": "Fischerspooner",
      "orig_artist": "Wire",
      "album": "#1",
      "year": "2003"
    },
    {
      "title": "Change My Life",
      "artist": "The Rosebuds",
      "orig_artist": "Spoon",
      "album": "Pearls: Volume One",
      "year": "2009"
    },
    {
      "title": "Here she comes now",
      "artist": "Galaxie 500",
      "orig_artist": "The Velvet Underground",
      "album": "This is Our Music",
      "year": "1990"
    },
    {
      "title": "Hey Joe",
      "artist": "Sonny & Cher",
      "orig_artist": "Jimmy Hendrix",
      "album": "The Singles + (CD2)",
      "year": "2000"
    },
    {
      "title": "Cut Dead",
      "artist": "Penny Broadhurst",
      "orig_artist": "Jesus and Mary Chain",
      "album": "The Jesus and Mary Chain Covers Project",
      "year": "2008"
    },
    {
      "title": "Last Nite",
      "artist": "The Detroit Cobras",
      "orig_artist": "the Strokes",
      "album": "In Covers We Trust 05",
      "year": "2007"
    },
    {
      "title": "Your Woman (orig. White Town)",
      "artist": "Dolby Anol",
      "orig_artist": "BL Rewind 2",
      "album": "Buffetlibre Rewind 2",
      "year": "2009"
    },
    {
      "title": "Tainted Love",
      "artist": "Gloria Jones",
      "orig_artist": "Soft Cell",
      "album": "Vixen",
      "year": "2025"
    },
    {
      "title": "Paint It Black",
      "artist": "The Love Sitars",
      "orig_artist": "The Rolling Stones",
      "album": "Single",
      "year": "1966"
    },
    {
      "title": "Fa Ce La",
      "artist": "Eastern Lane",
      "orig_artist": "The Feelies",
      "album": "Stop Me If You Think You've Heard This One Before…",
      "year": "2003"
    },
    {
      "title": "White Winter Hymnal",
      "artist": "Ruby Isle",
      "orig_artist": "Fleet Foxes",
      "album": "elbo.ws II",
      "year": "2009"
    }
  ],
  "html_path": "C:\\Users\\prob\\OneDrive\\Documents2\\hearmycovers\\playlists\\nuggets-38-covers-3\\index.html",
  "missing_art": []
}