{
  "name": "Nuggets 333 - Covers XXVIII - Quirky",
  "slug": "nuggets-333-covers-xxviii-quirky",
  "track_count": 24,
  "year_range": "1964–2023",
  "year_min": 1964,
  "year_max": 2023,
  "url": "playlists/nuggets-333-covers-xxviii-quirky/",
  "art_thumbnails": [
    "img/01.jpg",
    "img/02.jpg",
    "img/03.jpg",
    "img/04.jpg"
  ],
  "tracks": [
    {
      "title": "Animal",
      "artist": "The Suzan",
      "orig_artist": "Miike Snow",
      "album": "Golden Week For The Poco Poco Beat",
      "year": "2010"
    },
    {
      "title": "(Ghost) Riders In the Sky",
      "artist": "Johnny Cash",
      "orig_artist": "The Doors",
      "album": "The Essential Johnny Cash",
      "year": "2002"
    },
    {
      "title": "Young Folks",
      "artist": "Hideki Kaji//The Suzan",
      "orig_artist": "Peter Bjorn and John",
      "album": "Young Folks",
      "year": "2015"
    },
    {
      "title": "Human Nature",
      "artist": "Toro Y Moi",
      "orig_artist": "Michael Jackson",
      "album": "Chum Onah: BUTTERxFACE celebrates the music of M. Jackson",
      "year": "2009"
    },
    {
      "title": "(I Can't Get No) Satisfaction",
      "artist": "Devo",
      "orig_artist": "The Rolling Stones",
      "album": "Q: Are We Not Men? A: We Are Devo!",
      "year": "1988"
    },
    {
      "title": "Miss You",
      "artist": "The Dynamics",
      "orig_artist": "Rolling Stones",
      "album": "Version Excursions",
      "year": "2007"
    },
    {
      "title": "Please Please Please Let Me Get What I Want",
      "artist": "William Fitzsimmons",
      "orig_artist": "The Smiths",
      "album": "Please Please Please: A Tribute To The Smiths",
      "year": "2017"
    },
    {
      "title": "Warm Leatherette",
      "artist": "Rubin Steiner",
      "orig_artist": "The Normal",
      "album": "Weird hits, two covers & a love song",
      "year": "2008"
    },
    {
      "title": "Slippery People",
      "artist": "Mavis Staples/Win Butler/Regine Chassagne",
      "orig_artist": "Talking Heads",
      "album": "Slippery People (Live)",
      "year": "2017"
    },
    {
      "title": "(I Can't Get No) Satisfaction",
      "artist": "Bubblerock ",
      "orig_artist": "The Rolling Stones",
      "album": "Aquarium Drunkard Presents: Maison Dufrene II",
      "year": "2014"
    },
    {
      "title": "(I Can't Get No) Satisfaction (Alternate Vocal)",
      "artist": "The Supremes",
      "orig_artist": "The Rolling Stones",
      "album": "A' Go-Go: Expanded Edition",
      "year": "2017"
    },
    {
      "title": "She's Lost Control",
      "artist": "Girls Against Boys",
      "orig_artist": "Joy Division",
      "album": "She's Lost Control / Love Will Tear Us Apart",
      "year": "1995"
    },
    {
      "title": "Crying",
      "artist": "The Morning Benders",
      "orig_artist": "Roy Orbison",
      "album": "The Bedroom Covers",
      "year": "2007"
    },
    {
      "title": "Isolation",
      "artist": "The Smashing Pumpkins",
      "orig_artist": "Joy Division",
      "album": "Mellon Collie And The Infinite Sadness",
      "year": "2012"
    },
    {
      "title": "Wicked Game",
      "artist": "Grooms",
      "orig_artist": "Chris Isaak",
      "album": "Internet Single",
      "year": "2009"
    },
    {
      "title": "Run Run Run",
      "artist": "The Riats",
      "orig_artist": "Velvet Underground",
      "album": "Run, Run, Run",
      "year": "1967"
    },
    {
      "title": "Love Will Tear Us Apart",
      "artist": "Broken Social Scene",
      "orig_artist": "Joy Division",
      "album": "The Time Traveler's Wife Original Movie Sountrack",
      "year": "2009"
    },
    {
      "title": "Linger",
      "artist": "The Mathletes",
      "orig_artist": "The Cranberries",
      "album": "The Mathletes Present The Mathletes",
      "year": "2023"
    },
    {
      "title": "Twenty-Four Hours From Tulsa",
      "artist": "Dusty Springfield",
      "orig_artist": "Gene Pitney",
      "album": "A Girl Called Dusty",
      "year": "1964"
    },
    {
      "title": "Suzanne",
      "artist": "Flo Morrissey",
      "orig_artist": "Leonard Cohen",
      "album": "Gentlewoman, Ruby Man",
      "year": "2017"
    },
    {
      "title": "Das Model",
      "artist": "The Cardigans",
      "orig_artist": "Kraftwerk",
      "album": "For What It's Worth",
      "year": "2008"
    },
    {
      "title": "Time After Time",
      "artist": "Iron & Wine",
      "orig_artist": "Cyndi Lauper",
      "album": "Time After Time",
      "year": "2016"
    },
    {
      "title": "Cloudbusting Lovesong",
      "artist": "Swimmer One",
      "orig_artist": "Kate Bush",
      "album": "Outliers",
      "year": "2023"
    },
    {
      "title": "Starman",
      "artist": "Seu Jorge",
      "orig_artist": "David Bowie",
      "album": "The Life Aquatic Studio Sessions",
      "year": "2005"
    }
  ],
  "html_path": "C:\\Users\\prob\\OneDrive\\Documents2\\hearmycovers\\playlists\\nuggets-333-covers-xxviii-quirky\\index.html",
  "missing_art": []
}